jbussdieker/__main__.py
jbussdieker/cli/__init__.py
jbussdieker/cli/logging.py
jbussdieker/cli/main.py
jbussdieker-0.21.1.dist-info/licenses/LICENSE
jbussdieker-0.21.1.dist-info/METADATA
jbussdieker-0.21.1.dist-info/WHEEL
jbussdieker-0.21.1.dist-info/entry_points.txt
jbussdieker-0.21.1.dist-info/top_level.txt
jbussdieker-0.21.1.dist-info/RECORD
