Metadata-Version: 2.4
Name: jbussdieker
Version: 0.21.1
Summary: A modern Python development toolkit.
Author-email: "Joshua B. Bussdieker" <jbussdieker@gmail.com>
Maintainer-email: "Joshua B. Bussdieker" <jbussdieker@gmail.com>
License-Expression: MIT
Project-URL: Homepage, https://github.com/jbussdieker/jbussdieker
Project-URL: Documentation, https://github.com/jbussdieker/jbussdieker/blob/main/README.md
Project-URL: Repository, https://github.com/jbussdieker/jbussdieker
Project-URL: Issues, https://github.com/jbussdieker/jbussdieker/issues
Project-URL: Changelog, https://github.com/jbussdieker/jbussdieker/blob/main/CHANGELOG.md
Classifier: Topic :: Software Development :: Build Tools
Classifier: Development Status :: 3 - Alpha
Classifier: Programming Language :: Python :: 3
Classifier: Programming Language :: Python :: 3.9
Classifier: Programming Language :: Python :: 3.10
Classifier: Programming Language :: Python :: 3.11
Classifier: Programming Language :: Python :: 3.12
Classifier: Programming Language :: Python :: 3.13
Classifier: Operating System :: OS Independent
Classifier: Environment :: Console
Classifier: Intended Audience :: Developers
Classifier: Natural Language :: English
Classifier: Typing :: Typed
Requires-Python: >=3.9
License-File: LICENSE
Requires-Dist: jbussdieker-config>=0.5
Provides-Extra: all
Requires-Dist: jbussdieker-app>=0.4; extra == "all"
Requires-Dist: jbussdieker-commit>=0.4; extra == "all"
Requires-Dist: jbussdieker-project>=0.4; extra == "all"
Requires-Dist: jbussdieker-service>=0.5; extra == "all"
Requires-Dist: jbussdieker-storage>=0.2; extra == "all"
Provides-Extra: app
Requires-Dist: jbussdieker-app>=0.4; extra == "app"
Provides-Extra: commit
Requires-Dist: jbussdieker-commit>=0.4; extra == "commit"
Provides-Extra: project
Requires-Dist: jbussdieker-project>=0.4; extra == "project"
Provides-Extra: service
Requires-Dist: jbussdieker-service>=0.5; extra == "service"
Provides-Extra: storage
Requires-Dist: jbussdieker-storage>=0.2; extra == "storage"
Dynamic: license-file
